{
  "manifestVersion": "3.2",
  "admin": {
    "address": "0xDa13B230BCAB129F5C2b6Cf621e7eC6FA513aFfb",
    "txHash": "0x95de0e5d11afad2e8718e4f40b9aa80c3e8f6ddb712c5305d6badbc2a5ef699f"
  },
  "proxies": [
    {
      "address": "0xF403B6bf27DE9a86DeE9f39F20E406bcB25067bd",
      "txHash": "0x2106727ea3a0d4c7c9fce4176b9fb16e3bb756930b4dd9b45a617cc839d29863",
      "kind": "transparent"
    }
  ],
  "impls": {
    "9daa2de0be55235e53ea65391ac057d3bac9177c851ee45aab59e1ee9e54c3bd": {
      "address": "0x630840F5AEf440FD2DA198Ef323FeC58b538B8D9",
      "txHash": "0x68160fded332f5c2890570bc0344e4695fa87d2bf6979b069cf0c637de884943",
      "layout": {
        "solcVersion": "0.7.6",
        "storage": [
          {
            "label": "_initialized",
            "offset": 0,
            "slot": "0",
            "type": "t_bool",
            "contract": "Initializable",
            "src": "@openzeppelin/contracts-upgradeable/proxy/Initializable.sol:25"
          },
          {
            "label": "_initializing",
            "offset": 1,
            "slot": "0",
            "type": "t_bool",
            "contract": "Initializable",
            "src": "@openzeppelin/contracts-upgradeable/proxy/Initializable.sol:30"
          },
          {
            "label": "__gap",
            "offset": 0,
            "slot": "1",
            "type": "t_array(t_uint256)50_storage",
            "contract": "ContextUpgradeable",
            "src": "@openzeppelin/contracts-upgradeable/utils/ContextUpgradeable.sol:31"
          },
          {
            "label": "_owner",
            "offset": 0,
            "slot": "51",
            "type": "t_address",
            "contract": "OwnableUpgradeable",
            "src": "@openzeppelin/contracts-upgradeable/access/OwnableUpgradeable.sol:20"
          },
          {
            "label": "__gap",
            "offset": 0,
            "slot": "52",
            "type": "t_array(t_uint256)49_storage",
            "contract": "OwnableUpgradeable",
            "src": "@openzeppelin/contracts-upgradeable/access/OwnableUpgradeable.sol:74"
          },
          {
            "label": "royaltiesByTokenAndTokenId",
            "offset": 0,
            "slot": "101",
            "type": "t_mapping(t_bytes32,t_struct(RoyaltiesSet)15256_storage)",
            "contract": "RoyaltiesRegistry",
            "src": "@rarible/royalties-registry/contracts/RoyaltiesRegistry.sol:29"
          },
          {
            "label": "royaltiesByToken",
            "offset": 0,
            "slot": "102",
            "type": "t_mapping(t_address,t_struct(RoyaltiesSet)15256_storage)",
            "contract": "RoyaltiesRegistry",
            "src": "@rarible/royalties-registry/contracts/RoyaltiesRegistry.sol:31"
          },
          {
            "label": "royaltiesProviders",
            "offset": 0,
            "slot": "103",
            "type": "t_mapping(t_address,t_uint256)",
            "contract": "RoyaltiesRegistry",
            "src": "@rarible/royalties-registry/contracts/RoyaltiesRegistry.sol:33"
          },
          {
            "label": "__gap",
            "offset": 0,
            "slot": "104",
            "type": "t_array(t_uint256)46_storage",
            "contract": "RoyaltiesRegistry",
            "src": "@rarible/royalties-registry/contracts/RoyaltiesRegistry.sol:250"
          }
        ],
        "types": {
          "t_address": {
            "label": "address",
            "numberOfBytes": "20"
          },
          "t_address_payable": {
            "label": "address payable",
            "numberOfBytes": "20"
          },
          "t_array(t_struct(Part)14548_storage)dyn_storage": {
            "label": "struct LibPart.Part[]",
            "numberOfBytes": "32"
          },
          "t_array(t_uint256)46_storage": {
            "label": "uint256[46]",
            "numberOfBytes": "1472"
          },
          "t_array(t_uint256)49_storage": {
            "label": "uint256[49]",
            "numberOfBytes": "1568"
          },
          "t_array(t_uint256)50_storage": {
            "label": "uint256[50]",
            "numberOfBytes": "1600"
          },
          "t_bool": {
            "label": "bool",
            "numberOfBytes": "1"
          },
          "t_bytes32": {
            "label": "bytes32",
            "numberOfBytes": "32"
          },
          "t_mapping(t_address,t_struct(RoyaltiesSet)15256_storage)": {
            "label": "mapping(address => struct RoyaltiesRegistry.RoyaltiesSet)",
            "numberOfBytes": "32"
          },
          "t_mapping(t_address,t_uint256)": {
            "label": "mapping(address => uint256)",
            "numberOfBytes": "32"
          },
          "t_mapping(t_bytes32,t_struct(RoyaltiesSet)15256_storage)": {
            "label": "mapping(bytes32 => struct RoyaltiesRegistry.RoyaltiesSet)",
            "numberOfBytes": "32"
          },
          "t_struct(Part)14548_storage": {
            "label": "struct LibPart.Part",
            "members": [
              {
                "label": "account",
                "type": "t_address_payable",
                "offset": 0,
                "slot": "0"
              },
              {
                "label": "value",
                "type": "t_uint96",
                "offset": 20,
                "slot": "0"
              }
            ],
            "numberOfBytes": "32"
          },
          "t_struct(RoyaltiesSet)15256_storage": {
            "label": "struct RoyaltiesRegistry.RoyaltiesSet",
            "members": [
              {
                "label": "initialized",
                "type": "t_bool",
                "offset": 0,
                "slot": "0"
              },
              {
                "label": "royalties",
                "type": "t_array(t_struct(Part)14548_storage)dyn_storage",
                "offset": 0,
                "slot": "1"
              }
            ],
            "numberOfBytes": "64"
          },
          "t_uint256": {
            "label": "uint256",
            "numberOfBytes": "32"
          },
          "t_uint96": {
            "label": "uint96",
            "numberOfBytes": "12"
          }
        },
        "namespaces": {}
      }
    }
  }
}
