{
  "manifestVersion": "3.2",
  "admin": {
    "address": "0xc64E5D291CaEdF42b77fa9E50d5Fd46113227857",
    "txHash": "0x75fef70b31503b064eb4c93b2a4dd2e58578ad5ccdbfd29378cfd4c5eb6a7a26"
  },
  "proxies": [
    {
      "address": "0x551E4009116d489e3C5a98405A9c4B601D250B58",
      "txHash": "0x4bc70723311ca4e2a91a681517f5029817e9cbd823b8fa31b6095d0294cfa096",
      "kind": "transparent"
    },
    {
      "address": "0xEd9E4775a5d746fd4b36612fD0B2AfcB05b3147C",
      "txHash": "0x1e201e251a353af18dfa737c8bd6ca10ffae35ea3f9fc8ef82c9da2504f5279a",
      "kind": "transparent"
    },
    {
      "address": "0x268dF35c389Aa9e1ce0cd83CF8E5752b607dE90d",
      "txHash": "0x539a14341ccf8375122bc141a59df04465771358e3d7c854bdabd98e4047efea",
      "kind": "transparent"
    },
    {
      "address": "0x22f8CE349A3338B15D7fEfc013FA7739F5ea2ff7",
      "txHash": "0x622503ee1ce6d7d7f71141023c8b2237ec282bfb63f58fbf5e1038f92d1675b6",
      "kind": "transparent"
    },
    {
      "address": "0x90d65Fa5C3117A8f0C95b4EafD219E159b7102f9",
      "txHash": "0x0ead07bcf8b90bb8fd563e035258798ea8847ae013851a7fa26ebbe2745e41d5",
      "kind": "transparent"
    }
  ],
  "impls": {
    "167cf06f35a1a7276559971f892bfd508856b1102b2f73a807cb7785449a80d5": {
      "address": "0x3df054dA59B1c0D5d9CeE5EDc9B58798526023B5",
      "txHash": "0x44f5ee94585bc3065d41a315650ec8372f064fd75649c70e719f56be8f7aeb98",
      "layout": {
        "storage": [
          {
            "contract": "Initializable",
            "label": "_initialized",
            "type": "t_bool",
            "src": "../@openzeppelin/contracts-upgradeable/proxy/Initializable.sol:25"
          },
          {
            "contract": "Initializable",
            "label": "_initializing",
            "type": "t_bool",
            "src": "../@openzeppelin/contracts-upgradeable/proxy/Initializable.sol:30"
          },
          {
            "contract": "ContextUpgradeable",
            "label": "__gap",
            "type": "t_array(t_uint256)50_storage",
            "src": "../@openzeppelin/contracts-upgradeable/utils/ContextUpgradeable.sol:31"
          },
          {
            "contract": "OwnableUpgradeable",
            "label": "_owner",
            "type": "t_address",
            "src": "../@openzeppelin/contracts-upgradeable/access/OwnableUpgradeable.sol:20"
          },
          {
            "contract": "OwnableUpgradeable",
            "label": "__gap",
            "type": "t_array(t_uint256)49_storage",
            "src": "../@openzeppelin/contracts-upgradeable/access/OwnableUpgradeable.sol:74"
          },
          {
            "contract": "AssetMatcher",
            "label": "matchers",
            "type": "t_mapping(t_bytes4,t_address)",
            "src": "AssetMatcher.sol:13"
          },
          {
            "contract": "AssetMatcher",
            "label": "__gap",
            "type": "t_array(t_uint256)49_storage",
            "src": "AssetMatcher.sol:84"
          },
          {
            "contract": "TransferExecutor",
            "label": "proxies",
            "type": "t_mapping(t_bytes4,t_address)",
            "src": "TransferExecutor.sol:18"
          },
          {
            "contract": "TransferExecutor",
            "label": "__gap",
            "type": "t_array(t_uint256)49_storage",
            "src": "TransferExecutor.sol:58"
          },
          {
            "contract": "EIP712Upgradeable",
            "label": "_HASHED_NAME",
            "type": "t_bytes32",
            "src": "../@openzeppelin/contracts-upgradeable/drafts/EIP712Upgradeable.sol:27"
          },
          {
            "contract": "EIP712Upgradeable",
            "label": "_HASHED_VERSION",
            "type": "t_bytes32",
            "src": "../@openzeppelin/contracts-upgradeable/drafts/EIP712Upgradeable.sol:28"
          },
          {
            "contract": "EIP712Upgradeable",
            "label": "__gap",
            "type": "t_array(t_uint256)50_storage",
            "src": "../@openzeppelin/contracts-upgradeable/drafts/EIP712Upgradeable.sol:120"
          },
          {
            "contract": "OrderValidator",
            "label": "__gap",
            "type": "t_array(t_uint256)50_storage",
            "src": "OrderValidator.sol:43"
          },
          {
            "contract": "ExchangeV2Core",
            "label": "fills",
            "type": "t_mapping(t_bytes32,t_uint256)",
            "src": "ExchangeV2Core.sol:21"
          },
          {
            "contract": "ExchangeV2Core",
            "label": "__gap",
            "type": "t_array(t_uint256)49_storage",
            "src": "ExchangeV2Core.sol:96"
          },
          {
            "contract": "RaribleTransferManager",
            "label": "protocolFee",
            "type": "t_uint256",
            "src": "RaribleTransferManager.sol:22"
          },
          {
            "contract": "RaribleTransferManager",
            "label": "royaltiesRegistry",
            "type": "t_contract(IRoyaltiesProvider)4681",
            "src": "RaribleTransferManager.sol:23"
          },
          {
            "contract": "RaribleTransferManager",
            "label": "defaultFeeReceiver",
            "type": "t_address",
            "src": "RaribleTransferManager.sol:25"
          },
          {
            "contract": "RaribleTransferManager",
            "label": "feeReceivers",
            "type": "t_mapping(t_address,t_address)",
            "src": "RaribleTransferManager.sol:26"
          },
          {
            "contract": "RaribleTransferManager",
            "label": "__gap",
            "type": "t_array(t_uint256)46_storage",
            "src": "RaribleTransferManager.sol:205"
          }
        ],
        "types": {
          "t_uint256": {
            "label": "uint256"
          },
          "t_contract(IRoyaltiesProvider)4681": {
            "label": "contract IRoyaltiesProvider"
          },
          "t_address": {
            "label": "address"
          },
          "t_mapping(t_address,t_address)": {
            "label": "mapping(address => address)"
          },
          "t_array(t_uint256)46_storage": {
            "label": "uint256[46]"
          },
          "t_mapping(t_bytes32,t_uint256)": {
            "label": "mapping(bytes32 => uint256)"
          },
          "t_bytes32": {
            "label": "bytes32"
          },
          "t_array(t_uint256)49_storage": {
            "label": "uint256[49]"
          },
          "t_array(t_uint256)50_storage": {
            "label": "uint256[50]"
          },
          "t_mapping(t_bytes4,t_address)": {
            "label": "mapping(bytes4 => address)"
          },
          "t_bytes4": {
            "label": "bytes4"
          },
          "t_bool": {
            "label": "bool"
          }
        }
      }
    },
    "450d399b12e10cd2537fbd8cea600225f8b5377921cc0870a653a24587a78dbc": {
      "address": "0x71F499b457BCA8Bd6928Ba8Fb1B245b41Ec3e2d7",
      "txHash": "0xf823e6ea12b45c8a4f44f2a5c092d81abd8693fd58fe83f126bde259e3e52b60",
      "layout": {
        "storage": [
          {
            "contract": "Initializable",
            "label": "_initialized",
            "type": "t_bool",
            "src": "../@openzeppelin/contracts-upgradeable/proxy/Initializable.sol:25"
          },
          {
            "contract": "Initializable",
            "label": "_initializing",
            "type": "t_bool",
            "src": "../@openzeppelin/contracts-upgradeable/proxy/Initializable.sol:30"
          },
          {
            "contract": "ContextUpgradeable",
            "label": "__gap",
            "type": "t_array(t_uint256)50_storage",
            "src": "../@openzeppelin/contracts-upgradeable/utils/ContextUpgradeable.sol:31"
          },
          {
            "contract": "OwnableUpgradeable",
            "label": "_owner",
            "type": "t_address",
            "src": "../@openzeppelin/contracts-upgradeable/cryptography/ECDSAUpgradeable.sol:20"
          },
          {
            "contract": "OwnableUpgradeable",
            "label": "__gap",
            "type": "t_array(t_uint256)49_storage",
            "src": "../@openzeppelin/contracts-upgradeable/cryptography/ECDSAUpgradeable.sol:57"
          },
          {
            "contract": "AssetMatcher",
            "label": "matchers",
            "type": "t_mapping(t_bytes4,t_address)",
            "src": "AssetMatcher.sol:13"
          },
          {
            "contract": "AssetMatcher",
            "label": "__gap",
            "type": "t_array(t_uint256)49_storage",
            "src": "AssetMatcher.sol:77"
          },
          {
            "contract": "TransferExecutor",
            "label": "proxies",
            "type": "t_mapping(t_bytes4,t_address)",
            "src": "TransferExecutor.sol:18"
          },
          {
            "contract": "TransferExecutor",
            "label": "__gap",
            "type": "t_array(t_uint256)49_storage",
            "src": "TransferExecutor.sol:58"
          },
          {
            "contract": "EIP712Upgradeable",
            "label": "_HASHED_NAME",
            "type": "t_bytes32",
            "src": "../@openzeppelin/contracts-upgradeable/drafts/EIP712Upgradeable.sol:27"
          },
          {
            "contract": "EIP712Upgradeable",
            "label": "_HASHED_VERSION",
            "type": "t_bytes32",
            "src": "../@openzeppelin/contracts-upgradeable/drafts/EIP712Upgradeable.sol:28"
          },
          {
            "contract": "EIP712Upgradeable",
            "label": "__gap",
            "type": "t_array(t_uint256)50_storage",
            "src": "../@openzeppelin/contracts-upgradeable/drafts/EIP712Upgradeable.sol:120"
          },
          {
            "contract": "OrderValidator",
            "label": "__gap",
            "type": "t_array(t_uint256)50_storage",
            "src": "OrderValidator.sol:42"
          },
          {
            "contract": "ExchangeV2Core",
            "label": "fills",
            "type": "t_mapping(t_bytes32,t_uint256)",
            "src": "ExchangeV2Core.sol:21"
          },
          {
            "contract": "ExchangeV2Core",
            "label": "__gap",
            "type": "t_array(t_uint256)49_storage",
            "src": "ExchangeV2Core.sol:104"
          },
          {
            "contract": "RaribleTransferManager",
            "label": "protocolFee",
            "type": "t_uint256",
            "src": "RaribleTransferManager.sol:24"
          },
          {
            "contract": "RaribleTransferManager",
            "label": "royaltiesRegistry",
            "type": "t_contract(IRoyaltiesProvider)5103",
            "src": "RaribleTransferManager.sol:25"
          },
          {
            "contract": "RaribleTransferManager",
            "label": "defaultFeeReceiver",
            "type": "t_address",
            "src": "RaribleTransferManager.sol:27"
          },
          {
            "contract": "RaribleTransferManager",
            "label": "feeReceivers",
            "type": "t_mapping(t_address,t_address)",
            "src": "RaribleTransferManager.sol:28"
          },
          {
            "contract": "RaribleTransferManager",
            "label": "__gap",
            "type": "t_array(t_uint256)46_storage",
            "src": "RaribleTransferManager.sol:228"
          }
        ],
        "types": {
          "t_uint256": {
            "label": "uint256"
          },
          "t_contract(IRoyaltiesProvider)5103": {
            "label": "contract IRoyaltiesProvider"
          },
          "t_address": {
            "label": "address"
          },
          "t_mapping(t_address,t_address)": {
            "label": "mapping(address => address)"
          },
          "t_array(t_uint256)46_storage": {
            "label": "uint256[46]"
          },
          "t_mapping(t_bytes32,t_uint256)": {
            "label": "mapping(bytes32 => uint256)"
          },
          "t_bytes32": {
            "label": "bytes32"
          },
          "t_array(t_uint256)49_storage": {
            "label": "uint256[49]"
          },
          "t_array(t_uint256)50_storage": {
            "label": "uint256[50]"
          },
          "t_mapping(t_bytes4,t_address)": {
            "label": "mapping(bytes4 => address)"
          },
          "t_bytes4": {
            "label": "bytes4"
          },
          "t_bool": {
            "label": "bool"
          }
        }
      }
    },
    "80125e343244bbc38ed2615a0eff406d64e41db4dcb82035d9ce80158d7163fd": {
      "address": "0x84710B6a778b476db222879c42B2176FAeb8Bd03",
      "txHash": "0x4bc70723311ca4e2a91a681517f5029817e9cbd823b8fa31b6095d0294cfa096",
      "layout": {
        "storage": [
          {
            "contract": "Initializable",
            "label": "_initialized",
            "type": "t_bool",
            "src": "../@openzeppelin/contracts-upgradeable/proxy/Initializable.sol:25"
          },
          {
            "contract": "Initializable",
            "label": "_initializing",
            "type": "t_bool",
            "src": "../@openzeppelin/contracts-upgradeable/proxy/Initializable.sol:30"
          },
          {
            "contract": "ContextUpgradeable",
            "label": "__gap",
            "type": "t_array(t_uint256)50_storage",
            "src": "../@openzeppelin/contracts-upgradeable/utils/ContextUpgradeable.sol:31"
          },
          {
            "contract": "OwnableUpgradeable",
            "label": "_owner",
            "type": "t_address",
            "src": "../@openzeppelin/contracts-upgradeable/access/OwnableUpgradeable.sol:20"
          },
          {
            "contract": "OwnableUpgradeable",
            "label": "__gap",
            "type": "t_array(t_uint256)49_storage",
            "src": "../@openzeppelin/contracts-upgradeable/access/OwnableUpgradeable.sol:74"
          },
          {
            "contract": "AssetMatcher",
            "label": "matchers",
            "type": "t_mapping(t_bytes4,t_address)",
            "src": "AssetMatcher.sol:13"
          },
          {
            "contract": "AssetMatcher",
            "label": "__gap",
            "type": "t_array(t_uint256)49_storage",
            "src": "AssetMatcher.sol:77"
          },
          {
            "contract": "TransferExecutor",
            "label": "proxies",
            "type": "t_mapping(t_bytes4,t_address)",
            "src": "TransferExecutor.sol:18"
          },
          {
            "contract": "TransferExecutor",
            "label": "__gap",
            "type": "t_array(t_uint256)49_storage",
            "src": "TransferExecutor.sol:58"
          },
          {
            "contract": "EIP712Upgradeable",
            "label": "_HASHED_NAME",
            "type": "t_bytes32",
            "src": "../@openzeppelin/contracts-upgradeable/drafts/EIP712Upgradeable.sol:27"
          },
          {
            "contract": "EIP712Upgradeable",
            "label": "_HASHED_VERSION",
            "type": "t_bytes32",
            "src": "../@openzeppelin/contracts-upgradeable/drafts/EIP712Upgradeable.sol:28"
          },
          {
            "contract": "EIP712Upgradeable",
            "label": "__gap",
            "type": "t_array(t_uint256)50_storage",
            "src": "../@openzeppelin/contracts-upgradeable/drafts/EIP712Upgradeable.sol:120"
          },
          {
            "contract": "OrderValidator",
            "label": "__gap",
            "type": "t_array(t_uint256)50_storage",
            "src": "OrderValidator.sol:46"
          },
          {
            "contract": "ExchangeV2Core",
            "label": "fills",
            "type": "t_mapping(t_bytes32,t_uint256)",
            "src": "ExchangeV2Core.sol:21"
          },
          {
            "contract": "ExchangeV2Core",
            "label": "__gap",
            "type": "t_array(t_uint256)49_storage",
            "src": "ExchangeV2Core.sol:104"
          },
          {
            "contract": "RaribleTransferManager",
            "label": "protocolFee",
            "type": "t_uint256",
            "src": "RaribleTransferManager.sol:24"
          },
          {
            "contract": "RaribleTransferManager",
            "label": "royaltiesRegistry",
            "type": "t_contract(IRoyaltiesProvider)5126",
            "src": "RaribleTransferManager.sol:25"
          },
          {
            "contract": "RaribleTransferManager",
            "label": "defaultFeeReceiver",
            "type": "t_address",
            "src": "RaribleTransferManager.sol:27"
          },
          {
            "contract": "RaribleTransferManager",
            "label": "feeReceivers",
            "type": "t_mapping(t_address,t_address)",
            "src": "RaribleTransferManager.sol:28"
          },
          {
            "contract": "RaribleTransferManager",
            "label": "__gap",
            "type": "t_array(t_uint256)46_storage",
            "src": "RaribleTransferManager.sol:228"
          }
        ],
        "types": {
          "t_uint256": {
            "label": "uint256"
          },
          "t_contract(IRoyaltiesProvider)5126": {
            "label": "contract IRoyaltiesProvider"
          },
          "t_address": {
            "label": "address"
          },
          "t_mapping(t_address,t_address)": {
            "label": "mapping(address => address)"
          },
          "t_array(t_uint256)46_storage": {
            "label": "uint256[46]"
          },
          "t_mapping(t_bytes32,t_uint256)": {
            "label": "mapping(bytes32 => uint256)"
          },
          "t_bytes32": {
            "label": "bytes32"
          },
          "t_array(t_uint256)49_storage": {
            "label": "uint256[49]"
          },
          "t_array(t_uint256)50_storage": {
            "label": "uint256[50]"
          },
          "t_mapping(t_bytes4,t_address)": {
            "label": "mapping(bytes4 => address)"
          },
          "t_bytes4": {
            "label": "bytes4"
          },
          "t_bool": {
            "label": "bool"
          }
        }
      }
    },
    "3dbc68db4c5453149f7fe3e6ce91e0b7676bdd2f991d4ff27a9a8cdb77f9e30b": {
      "address": "0x9697ab36F564cA49552a72340108C3fD274F7F8c",
      "txHash": "0x1e201e251a353af18dfa737c8bd6ca10ffae35ea3f9fc8ef82c9da2504f5279a",
      "layout": {
        "storage": [
          {
            "contract": "Initializable",
            "label": "_initialized",
            "type": "t_bool",
            "src": "../@openzeppelin/contracts-upgradeable/proxy/Initializable.sol:25"
          },
          {
            "contract": "Initializable",
            "label": "_initializing",
            "type": "t_bool",
            "src": "../@openzeppelin/contracts-upgradeable/proxy/Initializable.sol:30"
          },
          {
            "contract": "ContextUpgradeable",
            "label": "__gap",
            "type": "t_array(t_uint256)50_storage",
            "src": "../@openzeppelin/contracts-upgradeable/utils/ContextUpgradeable.sol:31"
          },
          {
            "contract": "OwnableUpgradeable",
            "label": "_owner",
            "type": "t_address",
            "src": "../@openzeppelin/contracts-upgradeable/access/OwnableUpgradeable.sol:20"
          },
          {
            "contract": "OwnableUpgradeable",
            "label": "__gap",
            "type": "t_array(t_uint256)49_storage",
            "src": "../@openzeppelin/contracts-upgradeable/access/OwnableUpgradeable.sol:74"
          },
          {
            "contract": "RoyaltiesRegistry",
            "label": "royaltiesByTokenAndTokenId",
            "type": "t_mapping(t_bytes32,t_struct(RoyaltiesSet)68_storage)",
            "src": "RoyaltiesRegistry.sol:24"
          },
          {
            "contract": "RoyaltiesRegistry",
            "label": "royaltiesByToken",
            "type": "t_mapping(t_address,t_struct(RoyaltiesSet)68_storage)",
            "src": "RoyaltiesRegistry.sol:25"
          },
          {
            "contract": "RoyaltiesRegistry",
            "label": "royaltiesProviders",
            "type": "t_mapping(t_address,t_address)",
            "src": "RoyaltiesRegistry.sol:26"
          },
          {
            "contract": "RoyaltiesRegistry",
            "label": "__gap",
            "type": "t_array(t_uint256)46_storage",
            "src": "RoyaltiesRegistry.sol:140"
          }
        ],
        "types": {
          "t_mapping(t_bytes32,t_struct(RoyaltiesSet)68_storage)": {
            "label": "mapping(bytes32 => struct RoyaltiesRegistry.RoyaltiesSet)"
          },
          "t_bytes32": {
            "label": "bytes32"
          },
          "t_struct(RoyaltiesSet)68_storage": {
            "label": "struct RoyaltiesRegistry.RoyaltiesSet",
            "members": [
              {
                "label": "initialized",
                "type": "t_bool"
              },
              {
                "label": "royalties",
                "type": "t_array(t_struct(Part)1304_storage)dyn_storage"
              }
            ]
          },
          "t_bool": {
            "label": "bool"
          },
          "t_array(t_struct(Part)1304_storage)dyn_storage": {
            "label": "struct LibPart.Part[]"
          },
          "t_struct(Part)1304_storage": {
            "label": "struct LibPart.Part",
            "members": [
              {
                "label": "account",
                "type": "t_address_payable"
              },
              {
                "label": "value",
                "type": "t_uint96"
              }
            ]
          },
          "t_address_payable": {
            "label": "address payable"
          },
          "t_uint96": {
            "label": "uint96"
          },
          "t_mapping(t_address,t_struct(RoyaltiesSet)68_storage)": {
            "label": "mapping(address => struct RoyaltiesRegistry.RoyaltiesSet)"
          },
          "t_address": {
            "label": "address"
          },
          "t_mapping(t_address,t_address)": {
            "label": "mapping(address => address)"
          },
          "t_array(t_uint256)46_storage": {
            "label": "uint256[46]"
          },
          "t_uint256": {
            "label": "uint256"
          },
          "t_array(t_uint256)49_storage": {
            "label": "uint256[49]"
          },
          "t_array(t_uint256)50_storage": {
            "label": "uint256[50]"
          }
        }
      }
    },
    "fa23452d34b9df2d023e75a25b07e59237380c246969236e214a1709c29d90c5": {
      "address": "0x90c7EC8f92a29852AB28e978f7f8896B1030B531",
      "txHash": "0x8dec0b9a640a32df6510a260285d71f9102de75dfc6cc36fe684ee064fd0dd0d",
      "layout": {
        "storage": [
          {
            "contract": "Initializable",
            "label": "_initialized",
            "type": "t_bool",
            "src": "../@openzeppelin/contracts-upgradeable/proxy/Initializable.sol:25"
          },
          {
            "contract": "Initializable",
            "label": "_initializing",
            "type": "t_bool",
            "src": "../@openzeppelin/contracts-upgradeable/proxy/Initializable.sol:30"
          },
          {
            "contract": "ContextUpgradeable",
            "label": "__gap",
            "type": "t_array(t_uint256)50_storage",
            "src": "../@openzeppelin/contracts-upgradeable/utils/ContextUpgradeable.sol:31"
          },
          {
            "contract": "OwnableUpgradeable",
            "label": "_owner",
            "type": "t_address",
            "src": "../@openzeppelin/contracts-upgradeable/access/OwnableUpgradeable.sol:20"
          },
          {
            "contract": "OwnableUpgradeable",
            "label": "__gap",
            "type": "t_array(t_uint256)49_storage",
            "src": "../@openzeppelin/contracts-upgradeable/access/OwnableUpgradeable.sol:74"
          },
          {
            "contract": "ERC165Upgradeable",
            "label": "_supportedInterfaces",
            "type": "t_mapping(t_bytes4,t_bool)",
            "src": "../@openzeppelin/contracts-upgradeable/introspection/ERC165Upgradeable.sol:23"
          },
          {
            "contract": "ERC165Upgradeable",
            "label": "__gap",
            "type": "t_array(t_uint256)49_storage",
            "src": "../@openzeppelin/contracts-upgradeable/introspection/ERC165Upgradeable.sol:59"
          },
          {
            "contract": "ERC721Upgradeable",
            "label": "_holderTokens",
            "type": "t_mapping(t_address,t_struct(UintSet)7211_storage)",
            "src": "../@openzeppelin/contracts-upgradeable/token/ERC721/ERC721Upgradeable.sol:34"
          },
          {
            "contract": "ERC721Upgradeable",
            "label": "_tokenOwners",
            "type": "t_struct(UintToAddressMap)6588_storage",
            "src": "../@openzeppelin/contracts-upgradeable/token/ERC721/ERC721Upgradeable.sol:37"
          },
          {
            "contract": "ERC721Upgradeable",
            "label": "_tokenApprovals",
            "type": "t_mapping(t_uint256,t_address)",
            "src": "../@openzeppelin/contracts-upgradeable/token/ERC721/ERC721Upgradeable.sol:40"
          },
          {
            "contract": "ERC721Upgradeable",
            "label": "_operatorApprovals",
            "type": "t_mapping(t_address,t_mapping(t_address,t_bool))",
            "src": "../@openzeppelin/contracts-upgradeable/token/ERC721/ERC721Upgradeable.sol:43"
          },
          {
            "contract": "ERC721Upgradeable",
            "label": "_name",
            "type": "t_string_storage",
            "src": "../@openzeppelin/contracts-upgradeable/token/ERC721/ERC721Upgradeable.sol:46"
          },
          {
            "contract": "ERC721Upgradeable",
            "label": "_symbol",
            "type": "t_string_storage",
            "src": "../@openzeppelin/contracts-upgradeable/token/ERC721/ERC721Upgradeable.sol:49"
          },
          {
            "contract": "ERC721Upgradeable",
            "label": "_tokenURIs",
            "type": "t_mapping(t_uint256,t_string_storage)",
            "src": "../@openzeppelin/contracts-upgradeable/token/ERC721/ERC721Upgradeable.sol:52"
          },
          {
            "contract": "ERC721Upgradeable",
            "label": "_baseURI",
            "type": "t_string_storage",
            "src": "../@openzeppelin/contracts-upgradeable/token/ERC721/ERC721Upgradeable.sol:55"
          },
          {
            "contract": "ERC721Upgradeable",
            "label": "__gap",
            "type": "t_array(t_uint256)41_storage",
            "src": "../@openzeppelin/contracts-upgradeable/token/ERC721/ERC721Upgradeable.sol:480"
          },
          {
            "contract": "ERC721DefaultApproval",
            "label": "defaultApprovals",
            "type": "t_mapping(t_address,t_bool)",
            "src": "erc-721/ERC721DefaultApproval.sol:8"
          },
          {
            "contract": "ERC721DefaultApproval",
            "label": "__gap",
            "type": "t_array(t_uint256)50_storage",
            "src": "erc-721/ERC721DefaultApproval.sol:24"
          },
          {
            "contract": "ERC721BurnableUpgradeable",
            "label": "__gap",
            "type": "t_array(t_uint256)50_storage",
            "src": "../@openzeppelin/contracts-upgradeable/token/ERC721/ERC721BurnableUpgradeable.sol:34"
          },
          {
            "contract": "EIP712Upgradeable",
            "label": "_HASHED_NAME",
            "type": "t_bytes32",
            "src": "../@openzeppelin/contracts-upgradeable/drafts/EIP712Upgradeable.sol:27"
          },
          {
            "contract": "EIP712Upgradeable",
            "label": "_HASHED_VERSION",
            "type": "t_bytes32",
            "src": "../@openzeppelin/contracts-upgradeable/drafts/EIP712Upgradeable.sol:28"
          },
          {
            "contract": "EIP712Upgradeable",
            "label": "__gap",
            "type": "t_array(t_uint256)50_storage",
            "src": "../@openzeppelin/contracts-upgradeable/drafts/EIP712Upgradeable.sol:120"
          },
          {
            "contract": "ERC1271Validator",
            "label": "__gap",
            "type": "t_array(t_uint256)50_storage",
            "src": "erc-1271/ERC1271Validator.sol:30"
          },
          {
            "contract": "Mint721Validator",
            "label": "__gap",
            "type": "t_array(t_uint256)50_storage",
            "src": "erc-721/Mint721Validator.sol:16"
          },
          {
            "contract": "AbstractRoyalties",
            "label": "royalties",
            "type": "t_mapping(t_uint256,t_array(t_struct(Part)8486_storage)dyn_storage)",
            "src": "../@rarible/royalties/contracts/impl/AbstractRoyalties.sol:8"
          },
          {
            "contract": "ERC721Lazy",
            "label": "creators",
            "type": "t_mapping(t_uint256,t_array(t_struct(Part)8486_storage)dyn_storage)",
            "src": "erc-721/ERC721Lazy.sol:21"
          },
          {
            "contract": "ERC721Lazy",
            "label": "__gap",
            "type": "t_array(t_uint256)50_storage",
            "src": "erc-721/ERC721Lazy.sol:92"
          },
          {
            "contract": "HasContractURI",
            "label": "contractURI",
            "type": "t_string_storage",
            "src": "HasContractURI.sol:9"
          },
          {
            "contract": "HasContractURI",
            "label": "__gap",
            "type": "t_array(t_uint256)49_storage",
            "src": "HasContractURI.sol:29"
          },
          {
            "contract": "ERC721Base",
            "label": "__gap",
            "type": "t_array(t_uint256)50_storage",
            "src": "erc-721/ERC721Base.sol:30"
          },
          {
            "contract": "ERC721Rarible",
            "label": "__gap",
            "type": "t_array(t_uint256)50_storage",
            "src": "erc-721/ERC721Rarible.sol:25"
          }
        ],
        "types": {
          "t_array(t_uint256)50_storage": {
            "label": "uint256[50]"
          },
          "t_uint256": {
            "label": "uint256"
          },
          "t_string_storage": {
            "label": "string"
          },
          "t_array(t_uint256)49_storage": {
            "label": "uint256[49]"
          },
          "t_mapping(t_uint256,t_array(t_struct(Part)8486_storage)dyn_storage)": {
            "label": "mapping(uint256 => struct LibPart.Part[])"
          },
          "t_array(t_struct(Part)8486_storage)dyn_storage": {
            "label": "struct LibPart.Part[]"
          },
          "t_struct(Part)8486_storage": {
            "label": "struct LibPart.Part",
            "members": [
              {
                "label": "account",
                "type": "t_address_payable"
              },
              {
                "label": "value",
                "type": "t_uint96"
              }
            ]
          },
          "t_address_payable": {
            "label": "address payable"
          },
          "t_uint96": {
            "label": "uint96"
          },
          "t_bytes32": {
            "label": "bytes32"
          },
          "t_mapping(t_address,t_bool)": {
            "label": "mapping(address => bool)"
          },
          "t_address": {
            "label": "address"
          },
          "t_bool": {
            "label": "bool"
          },
          "t_mapping(t_address,t_struct(UintSet)7211_storage)": {
            "label": "mapping(address => struct EnumerableSetUpgradeable.UintSet)"
          },
          "t_struct(UintSet)7211_storage": {
            "label": "struct EnumerableSetUpgradeable.UintSet",
            "members": [
              {
                "label": "_inner",
                "type": "t_struct(Set)6825_storage"
              }
            ]
          },
          "t_struct(Set)6825_storage": {
            "label": "struct EnumerableSetUpgradeable.Set",
            "members": [
              {
                "label": "_values",
                "type": "t_array(t_bytes32)dyn_storage"
              },
              {
                "label": "_indexes",
                "type": "t_mapping(t_bytes32,t_uint256)"
              }
            ]
          },
          "t_array(t_bytes32)dyn_storage": {
            "label": "bytes32[]"
          },
          "t_mapping(t_bytes32,t_uint256)": {
            "label": "mapping(bytes32 => uint256)"
          },
          "t_struct(UintToAddressMap)6588_storage": {
            "label": "struct EnumerableMapUpgradeable.UintToAddressMap",
            "members": [
              {
                "label": "_inner",
                "type": "t_struct(Map)6270_storage"
              }
            ]
          },
          "t_struct(Map)6270_storage": {
            "label": "struct EnumerableMapUpgradeable.Map",
            "members": [
              {
                "label": "_entries",
                "type": "t_array(t_struct(MapEntry)6262_storage)dyn_storage"
              },
              {
                "label": "_indexes",
                "type": "t_mapping(t_bytes32,t_uint256)"
              }
            ]
          },
          "t_array(t_struct(MapEntry)6262_storage)dyn_storage": {
            "label": "struct EnumerableMapUpgradeable.MapEntry[]"
          },
          "t_struct(MapEntry)6262_storage": {
            "label": "struct EnumerableMapUpgradeable.MapEntry",
            "members": [
              {
                "label": "_key",
                "type": "t_bytes32"
              },
              {
                "label": "_value",
                "type": "t_bytes32"
              }
            ]
          },
          "t_mapping(t_uint256,t_address)": {
            "label": "mapping(uint256 => address)"
          },
          "t_mapping(t_address,t_mapping(t_address,t_bool))": {
            "label": "mapping(address => mapping(address => bool))"
          },
          "t_mapping(t_uint256,t_string_storage)": {
            "label": "mapping(uint256 => string)"
          },
          "t_array(t_uint256)41_storage": {
            "label": "uint256[41]"
          },
          "t_mapping(t_bytes4,t_bool)": {
            "label": "mapping(bytes4 => bool)"
          },
          "t_bytes4": {
            "label": "bytes4"
          }
        }
      }
    },
    "819f45e97ee3e98b9c5d58fcf49d34afbbed0bd8c02ea0f5348f089448d6c0af": {
      "address": "0xfDB27dC8Fd586d67d08e7d0BeFFCB1CD812c71c6",
      "txHash": "0x539a14341ccf8375122bc141a59df04465771358e3d7c854bdabd98e4047efea",
      "layout": {
        "storage": [
          {
            "contract": "Initializable",
            "label": "_initialized",
            "type": "t_bool",
            "src": "../@openzeppelin/contracts-upgradeable/proxy/Initializable.sol:25"
          },
          {
            "contract": "Initializable",
            "label": "_initializing",
            "type": "t_bool",
            "src": "../@openzeppelin/contracts-upgradeable/proxy/Initializable.sol:30"
          },
          {
            "contract": "ContextUpgradeable",
            "label": "__gap",
            "type": "t_array(t_uint256)50_storage",
            "src": "../@openzeppelin/contracts-upgradeable/utils/ContextUpgradeable.sol:31"
          },
          {
            "contract": "OwnableUpgradeable",
            "label": "_owner",
            "type": "t_address",
            "src": "../@openzeppelin/contracts-upgradeable/access/OwnableUpgradeable.sol:20"
          },
          {
            "contract": "OwnableUpgradeable",
            "label": "__gap",
            "type": "t_array(t_uint256)49_storage",
            "src": "../@openzeppelin/contracts-upgradeable/access/OwnableUpgradeable.sol:74"
          },
          {
            "contract": "ERC165Upgradeable",
            "label": "_supportedInterfaces",
            "type": "t_mapping(t_bytes4,t_bool)",
            "src": "../@openzeppelin/contracts-upgradeable/introspection/ERC165Upgradeable.sol:23"
          },
          {
            "contract": "ERC165Upgradeable",
            "label": "__gap",
            "type": "t_array(t_uint256)49_storage",
            "src": "../@openzeppelin/contracts-upgradeable/introspection/ERC165Upgradeable.sol:59"
          },
          {
            "contract": "ERC1155Upgradeable",
            "label": "_balances",
            "type": "t_mapping(t_uint256,t_mapping(t_address,t_uint256))",
            "src": "../@openzeppelin/contracts-upgradeable/token/ERC1155/ERC1155Upgradeable.sol:27"
          },
          {
            "contract": "ERC1155Upgradeable",
            "label": "_operatorApprovals",
            "type": "t_mapping(t_address,t_mapping(t_address,t_bool))",
            "src": "../@openzeppelin/contracts-upgradeable/token/ERC1155/ERC1155Upgradeable.sol:30"
          },
          {
            "contract": "ERC1155Upgradeable",
            "label": "_uri",
            "type": "t_string_storage",
            "src": "../@openzeppelin/contracts-upgradeable/token/ERC1155/ERC1155Upgradeable.sol:33"
          },
          {
            "contract": "ERC1155Upgradeable",
            "label": "__gap",
            "type": "t_array(t_uint256)47_storage",
            "src": "../@openzeppelin/contracts-upgradeable/token/ERC1155/ERC1155Upgradeable.sol:421"
          },
          {
            "contract": "ERC1155DefaultApproval",
            "label": "defaultApprovals",
            "type": "t_mapping(t_address,t_bool)",
            "src": "erc-1155/ERC1155DefaultApproval.sol:8"
          },
          {
            "contract": "ERC1155DefaultApproval",
            "label": "__gap",
            "type": "t_array(t_uint256)50_storage",
            "src": "erc-1155/ERC1155DefaultApproval.sol:20"
          },
          {
            "contract": "ERC1155BurnableUpgradeable",
            "label": "__gap",
            "type": "t_array(t_uint256)50_storage",
            "src": "../@openzeppelin/contracts-upgradeable/token/ERC1155/ERC1155BurnableUpgradeable.sol:40"
          },
          {
            "contract": "ERC1155BaseURI",
            "label": "_tokenURIs",
            "type": "t_mapping(t_uint256,t_string_storage)",
            "src": "erc-1155/ERC1155BaseURI.sol:12"
          },
          {
            "contract": "ERC1155BaseURI",
            "label": "_baseURI",
            "type": "t_string_storage",
            "src": "erc-1155/ERC1155BaseURI.sol:15"
          },
          {
            "contract": "ERC1155BaseURI",
            "label": "__gap",
            "type": "t_array(t_uint256)50_storage",
            "src": "erc-1155/ERC1155BaseURI.sol:67"
          },
          {
            "contract": "EIP712Upgradeable",
            "label": "_HASHED_NAME",
            "type": "t_bytes32",
            "src": "../@openzeppelin/contracts-upgradeable/drafts/EIP712Upgradeable.sol:27"
          },
          {
            "contract": "EIP712Upgradeable",
            "label": "_HASHED_VERSION",
            "type": "t_bytes32",
            "src": "../@openzeppelin/contracts-upgradeable/drafts/EIP712Upgradeable.sol:28"
          },
          {
            "contract": "EIP712Upgradeable",
            "label": "__gap",
            "type": "t_array(t_uint256)50_storage",
            "src": "../@openzeppelin/contracts-upgradeable/drafts/EIP712Upgradeable.sol:120"
          },
          {
            "contract": "ERC1271Validator",
            "label": "__gap",
            "type": "t_array(t_uint256)50_storage",
            "src": "erc-1271/ERC1271Validator.sol:30"
          },
          {
            "contract": "Mint1155Validator",
            "label": "__gap",
            "type": "t_array(t_uint256)50_storage",
            "src": "erc-1155/Mint1155Validator.sol:16"
          },
          {
            "contract": "AbstractRoyalties",
            "label": "royalties",
            "type": "t_mapping(t_uint256,t_array(t_struct(Part)8486_storage)dyn_storage)",
            "src": "../@rarible/royalties/contracts/impl/AbstractRoyalties.sol:8"
          },
          {
            "contract": "ERC1155Lazy",
            "label": "creators",
            "type": "t_mapping(t_uint256,t_array(t_struct(Part)8486_storage)dyn_storage)",
            "src": "erc-1155/ERC1155Lazy.sol:20"
          },
          {
            "contract": "ERC1155Lazy",
            "label": "supply",
            "type": "t_mapping(t_uint256,t_uint256)",
            "src": "erc-1155/ERC1155Lazy.sol:21"
          },
          {
            "contract": "ERC1155Lazy",
            "label": "minted",
            "type": "t_mapping(t_uint256,t_uint256)",
            "src": "erc-1155/ERC1155Lazy.sol:22"
          },
          {
            "contract": "ERC1155Lazy",
            "label": "__gap",
            "type": "t_array(t_uint256)50_storage",
            "src": "erc-1155/ERC1155Lazy.sol:121"
          },
          {
            "contract": "HasContractURI",
            "label": "contractURI",
            "type": "t_string_storage",
            "src": "HasContractURI.sol:9"
          },
          {
            "contract": "HasContractURI",
            "label": "__gap",
            "type": "t_array(t_uint256)49_storage",
            "src": "HasContractURI.sol:29"
          },
          {
            "contract": "ERC1155Base",
            "label": "name",
            "type": "t_string_storage",
            "src": "erc-1155/ERC1155Base.sol:14"
          },
          {
            "contract": "ERC1155Base",
            "label": "symbol",
            "type": "t_string_storage",
            "src": "erc-1155/ERC1155Base.sol:15"
          },
          {
            "contract": "ERC1155Base",
            "label": "__gap",
            "type": "t_array(t_uint256)50_storage",
            "src": "erc-1155/ERC1155Base.sol:42"
          },
          {
            "contract": "ERC1155Rarible",
            "label": "__gap",
            "type": "t_array(t_uint256)50_storage",
            "src": "erc-1155/ERC1155Rarible.sol:25"
          }
        ],
        "types": {
          "t_array(t_uint256)50_storage": {
            "label": "uint256[50]"
          },
          "t_uint256": {
            "label": "uint256"
          },
          "t_string_storage": {
            "label": "string"
          },
          "t_array(t_uint256)49_storage": {
            "label": "uint256[49]"
          },
          "t_mapping(t_uint256,t_array(t_struct(Part)8486_storage)dyn_storage)": {
            "label": "mapping(uint256 => struct LibPart.Part[])"
          },
          "t_array(t_struct(Part)8486_storage)dyn_storage": {
            "label": "struct LibPart.Part[]"
          },
          "t_struct(Part)8486_storage": {
            "label": "struct LibPart.Part",
            "members": [
              {
                "label": "account",
                "type": "t_address_payable"
              },
              {
                "label": "value",
                "type": "t_uint96"
              }
            ]
          },
          "t_address_payable": {
            "label": "address payable"
          },
          "t_uint96": {
            "label": "uint96"
          },
          "t_mapping(t_uint256,t_uint256)": {
            "label": "mapping(uint256 => uint256)"
          },
          "t_bytes32": {
            "label": "bytes32"
          },
          "t_mapping(t_uint256,t_string_storage)": {
            "label": "mapping(uint256 => string)"
          },
          "t_mapping(t_address,t_bool)": {
            "label": "mapping(address => bool)"
          },
          "t_address": {
            "label": "address"
          },
          "t_bool": {
            "label": "bool"
          },
          "t_mapping(t_uint256,t_mapping(t_address,t_uint256))": {
            "label": "mapping(uint256 => mapping(address => uint256))"
          },
          "t_mapping(t_address,t_uint256)": {
            "label": "mapping(address => uint256)"
          },
          "t_mapping(t_address,t_mapping(t_address,t_bool))": {
            "label": "mapping(address => mapping(address => bool))"
          },
          "t_array(t_uint256)47_storage": {
            "label": "uint256[47]"
          },
          "t_mapping(t_bytes4,t_bool)": {
            "label": "mapping(bytes4 => bool)"
          },
          "t_bytes4": {
            "label": "bytes4"
          }
        }
      }
    },
    "56c5beb51a253ca41865c41f03f8906ac979632807be7dcd655fc4f3bf0c2bfe": {
      "address": "0x25F2AE015Cf691D79EF36f9C4825873edbAE37c7",
      "txHash": "0xb0ef6edca8d64ade0b0fb9d9fb840e54d73789b42a9c10cb923715c6bd42d902",
      "layout": {
        "storage": [
          {
            "contract": "Initializable",
            "label": "_initialized",
            "type": "t_bool",
            "src": "../@openzeppelin/contracts-upgradeable/proxy/Initializable.sol:25"
          },
          {
            "contract": "Initializable",
            "label": "_initializing",
            "type": "t_bool",
            "src": "../@openzeppelin/contracts-upgradeable/proxy/Initializable.sol:30"
          },
          {
            "contract": "ContextUpgradeable",
            "label": "__gap",
            "type": "t_array(t_uint256)50_storage",
            "src": "../@openzeppelin/contracts-upgradeable/utils/ContextUpgradeable.sol:31"
          },
          {
            "contract": "OwnableUpgradeable",
            "label": "_owner",
            "type": "t_address",
            "src": "../@openzeppelin/contracts-upgradeable/access/OwnableUpgradeable.sol:20"
          },
          {
            "contract": "OwnableUpgradeable",
            "label": "__gap",
            "type": "t_array(t_uint256)49_storage",
            "src": "../@openzeppelin/contracts-upgradeable/access/OwnableUpgradeable.sol:74"
          },
          {
            "contract": "ERC165Upgradeable",
            "label": "_supportedInterfaces",
            "type": "t_mapping(t_bytes4,t_bool)",
            "src": "../@openzeppelin/contracts-upgradeable/introspection/ERC165Upgradeable.sol:23"
          },
          {
            "contract": "ERC165Upgradeable",
            "label": "__gap",
            "type": "t_array(t_uint256)49_storage",
            "src": "../@openzeppelin/contracts-upgradeable/introspection/ERC165Upgradeable.sol:59"
          },
          {
            "contract": "ERC721Upgradeable",
            "label": "_holderTokens",
            "type": "t_mapping(t_address,t_struct(UintSet)2736_storage)",
            "src": "../@rarible/tokens/contracts/erc-721/ERC721Upgradeable.sol:34"
          },
          {
            "contract": "ERC721Upgradeable",
            "label": "_tokenOwners",
            "type": "t_struct(UintToAddressMap)2113_storage",
            "src": "../@rarible/tokens/contracts/erc-721/ERC721Upgradeable.sol:37"
          },
          {
            "contract": "ERC721Upgradeable",
            "label": "_tokenApprovals",
            "type": "t_mapping(t_uint256,t_address)",
            "src": "../@rarible/tokens/contracts/erc-721/ERC721Upgradeable.sol:40"
          },
          {
            "contract": "ERC721Upgradeable",
            "label": "_operatorApprovals",
            "type": "t_mapping(t_address,t_mapping(t_address,t_bool))",
            "src": "../@rarible/tokens/contracts/erc-721/ERC721Upgradeable.sol:43"
          },
          {
            "contract": "ERC721Upgradeable",
            "label": "_name",
            "type": "t_string_storage",
            "src": "../@rarible/tokens/contracts/erc-721/ERC721Upgradeable.sol:46"
          },
          {
            "contract": "ERC721Upgradeable",
            "label": "_symbol",
            "type": "t_string_storage",
            "src": "../@rarible/tokens/contracts/erc-721/ERC721Upgradeable.sol:49"
          },
          {
            "contract": "ERC721Upgradeable",
            "label": "_tokenURIs",
            "type": "t_mapping(t_uint256,t_string_storage)",
            "src": "../@rarible/tokens/contracts/erc-721/ERC721Upgradeable.sol:52"
          },
          {
            "contract": "ERC721Upgradeable",
            "label": "_baseURI",
            "type": "t_string_storage",
            "src": "../@rarible/tokens/contracts/erc-721/ERC721Upgradeable.sol:55"
          },
          {
            "contract": "ERC721Upgradeable",
            "label": "__gap",
            "type": "t_array(t_uint256)41_storage",
            "src": "../@rarible/tokens/contracts/erc-721/ERC721Upgradeable.sol:480"
          },
          {
            "contract": "ERC721DefaultApproval",
            "label": "defaultApprovals",
            "type": "t_mapping(t_address,t_bool)",
            "src": "../@rarible/tokens/contracts/erc-721/ERC721DefaultApproval.sol:8"
          },
          {
            "contract": "ERC721DefaultApproval",
            "label": "__gap",
            "type": "t_array(t_uint256)50_storage",
            "src": "../@rarible/tokens/contracts/erc-721/ERC721DefaultApproval.sol:24"
          },
          {
            "contract": "ERC721BurnableUpgradeable",
            "label": "__gap",
            "type": "t_array(t_uint256)50_storage",
            "src": "../@rarible/tokens/contracts/erc-721/ERC721BurnableUpgradeable.sol:34"
          },
          {
            "contract": "EIP712Upgradeable",
            "label": "_HASHED_NAME",
            "type": "t_bytes32",
            "src": "../@openzeppelin/contracts-upgradeable/drafts/EIP712Upgradeable.sol:27"
          },
          {
            "contract": "EIP712Upgradeable",
            "label": "_HASHED_VERSION",
            "type": "t_bytes32",
            "src": "../@openzeppelin/contracts-upgradeable/drafts/EIP712Upgradeable.sol:28"
          },
          {
            "contract": "EIP712Upgradeable",
            "label": "__gap",
            "type": "t_array(t_uint256)50_storage",
            "src": "../@openzeppelin/contracts-upgradeable/drafts/EIP712Upgradeable.sol:120"
          },
          {
            "contract": "ERC1271Validator",
            "label": "__gap",
            "type": "t_array(t_uint256)50_storage",
            "src": "../@rarible/tokens/contracts/erc-1271/ERC1271Validator.sol:30"
          },
          {
            "contract": "Mint721Validator",
            "label": "__gap",
            "type": "t_array(t_uint256)50_storage",
            "src": "../@rarible/tokens/contracts/Mint721Validator.sol:16"
          },
          {
            "contract": "AbstractRoyalties",
            "label": "royalties",
            "type": "t_mapping(t_uint256,t_array(t_struct(Part)9174_storage)dyn_storage)",
            "src": "../@rarible/royalties/contracts/impl/AbstractRoyalties.sol:8"
          },
          {
            "contract": "ERC721Lazy",
            "label": "creators",
            "type": "t_mapping(t_uint256,t_array(t_struct(Part)9174_storage)dyn_storage)",
            "src": "../@rarible/tokens/contracts/erc-721/ERC721Lazy.sol:23"
          },
          {
            "contract": "ERC721Lazy",
            "label": "__gap",
            "type": "t_array(t_uint256)50_storage",
            "src": "../@rarible/tokens/contracts/erc-721/ERC721Lazy.sol:113"
          },
          {
            "contract": "HasContractURI",
            "label": "contractURI",
            "type": "t_string_storage",
            "src": "../@rarible/tokens/contracts/HasContractURI.sol:9"
          },
          {
            "contract": "HasContractURI",
            "label": "__gap",
            "type": "t_array(t_uint256)49_storage",
            "src": "../@rarible/tokens/contracts/HasContractURI.sol:29"
          },
          {
            "contract": "ERC721Base",
            "label": "__gap",
            "type": "t_array(t_uint256)50_storage",
            "src": "../@rarible/tokens/contracts/erc-721/ERC721Base.sol:34"
          },
          {
            "contract": "ERC721Rarible",
            "label": "__gap",
            "type": "t_array(t_uint256)50_storage",
            "src": "../@rarible/tokens/contracts/erc-721/ERC721Rarible.sol:30"
          }
        ],
        "types": {
          "t_array(t_uint256)50_storage": {
            "label": "uint256[50]"
          },
          "t_uint256": {
            "label": "uint256"
          },
          "t_string_storage": {
            "label": "string"
          },
          "t_array(t_uint256)49_storage": {
            "label": "uint256[49]"
          },
          "t_mapping(t_uint256,t_array(t_struct(Part)9174_storage)dyn_storage)": {
            "label": "mapping(uint256 => struct LibPart.Part[])"
          },
          "t_array(t_struct(Part)9174_storage)dyn_storage": {
            "label": "struct LibPart.Part[]"
          },
          "t_struct(Part)9174_storage": {
            "label": "struct LibPart.Part",
            "members": [
              {
                "label": "account",
                "type": "t_address_payable"
              },
              {
                "label": "value",
                "type": "t_uint96"
              }
            ]
          },
          "t_address_payable": {
            "label": "address payable"
          },
          "t_uint96": {
            "label": "uint96"
          },
          "t_bytes32": {
            "label": "bytes32"
          },
          "t_mapping(t_address,t_bool)": {
            "label": "mapping(address => bool)"
          },
          "t_address": {
            "label": "address"
          },
          "t_bool": {
            "label": "bool"
          },
          "t_mapping(t_address,t_struct(UintSet)2736_storage)": {
            "label": "mapping(address => struct EnumerableSetUpgradeable.UintSet)"
          },
          "t_struct(UintSet)2736_storage": {
            "label": "struct EnumerableSetUpgradeable.UintSet",
            "members": [
              {
                "label": "_inner",
                "type": "t_struct(Set)2350_storage"
              }
            ]
          },
          "t_struct(Set)2350_storage": {
            "label": "struct EnumerableSetUpgradeable.Set",
            "members": [
              {
                "label": "_values",
                "type": "t_array(t_bytes32)dyn_storage"
              },
              {
                "label": "_indexes",
                "type": "t_mapping(t_bytes32,t_uint256)"
              }
            ]
          },
          "t_array(t_bytes32)dyn_storage": {
            "label": "bytes32[]"
          },
          "t_mapping(t_bytes32,t_uint256)": {
            "label": "mapping(bytes32 => uint256)"
          },
          "t_struct(UintToAddressMap)2113_storage": {
            "label": "struct EnumerableMapUpgradeable.UintToAddressMap",
            "members": [
              {
                "label": "_inner",
                "type": "t_struct(Map)1795_storage"
              }
            ]
          },
          "t_struct(Map)1795_storage": {
            "label": "struct EnumerableMapUpgradeable.Map",
            "members": [
              {
                "label": "_entries",
                "type": "t_array(t_struct(MapEntry)1787_storage)dyn_storage"
              },
              {
                "label": "_indexes",
                "type": "t_mapping(t_bytes32,t_uint256)"
              }
            ]
          },
          "t_array(t_struct(MapEntry)1787_storage)dyn_storage": {
            "label": "struct EnumerableMapUpgradeable.MapEntry[]"
          },
          "t_struct(MapEntry)1787_storage": {
            "label": "struct EnumerableMapUpgradeable.MapEntry",
            "members": [
              {
                "label": "_key",
                "type": "t_bytes32"
              },
              {
                "label": "_value",
                "type": "t_bytes32"
              }
            ]
          },
          "t_mapping(t_uint256,t_address)": {
            "label": "mapping(uint256 => address)"
          },
          "t_mapping(t_address,t_mapping(t_address,t_bool))": {
            "label": "mapping(address => mapping(address => bool))"
          },
          "t_mapping(t_uint256,t_string_storage)": {
            "label": "mapping(uint256 => string)"
          },
          "t_array(t_uint256)41_storage": {
            "label": "uint256[41]"
          },
          "t_mapping(t_bytes4,t_bool)": {
            "label": "mapping(bytes4 => bool)"
          },
          "t_bytes4": {
            "label": "bytes4"
          }
        }
      }
    },
    "9c2b073f288dd58cddd929ebb41b83f20bb35d8c5b0256f9f61d6ad2c6d3f62a": {
      "address": "0x276C8308d548d9ca736071f3d39D5dFCd85ba463",
      "txHash": "0x5396be92e4247f479f6235079f1b37cdf7d59a9264b3313eb99c8607e0e01014",
      "layout": {
        "storage": [
          {
            "contract": "Initializable",
            "label": "_initialized",
            "type": "t_bool",
            "src": "../@openzeppelin/contracts-upgradeable/proxy/Initializable.sol:25"
          },
          {
            "contract": "Initializable",
            "label": "_initializing",
            "type": "t_bool",
            "src": "../@openzeppelin/contracts-upgradeable/proxy/Initializable.sol:30"
          },
          {
            "contract": "ContextUpgradeable",
            "label": "__gap",
            "type": "t_array(t_uint256)50_storage",
            "src": "../@openzeppelin/contracts-upgradeable/utils/ContextUpgradeable.sol:31"
          },
          {
            "contract": "OwnableUpgradeable",
            "label": "_owner",
            "type": "t_address",
            "src": "../@openzeppelin/contracts-upgradeable/access/OwnableUpgradeable.sol:20"
          },
          {
            "contract": "OwnableUpgradeable",
            "label": "__gap",
            "type": "t_array(t_uint256)49_storage",
            "src": "../@openzeppelin/contracts-upgradeable/access/OwnableUpgradeable.sol:74"
          },
          {
            "contract": "ERC165Upgradeable",
            "label": "_supportedInterfaces",
            "type": "t_mapping(t_bytes4,t_bool)",
            "src": "../@openzeppelin/contracts-upgradeable/introspection/ERC165Upgradeable.sol:23"
          },
          {
            "contract": "ERC165Upgradeable",
            "label": "__gap",
            "type": "t_array(t_uint256)49_storage",
            "src": "../@openzeppelin/contracts-upgradeable/introspection/ERC165Upgradeable.sol:59"
          },
          {
            "contract": "ERC1155Upgradeable",
            "label": "_balances",
            "type": "t_mapping(t_uint256,t_mapping(t_address,t_uint256))",
            "src": "../@rarible/tokens/contracts/erc-1155/ERC1155Upgradeable.sol:27"
          },
          {
            "contract": "ERC1155Upgradeable",
            "label": "_operatorApprovals",
            "type": "t_mapping(t_address,t_mapping(t_address,t_bool))",
            "src": "../@rarible/tokens/contracts/erc-1155/ERC1155Upgradeable.sol:30"
          },
          {
            "contract": "ERC1155Upgradeable",
            "label": "_uri",
            "type": "t_string_storage",
            "src": "../@rarible/tokens/contracts/erc-1155/ERC1155Upgradeable.sol:33"
          },
          {
            "contract": "ERC1155Upgradeable",
            "label": "__gap",
            "type": "t_array(t_uint256)47_storage",
            "src": "../@rarible/tokens/contracts/erc-1155/ERC1155Upgradeable.sol:421"
          },
          {
            "contract": "ERC1155DefaultApproval",
            "label": "defaultApprovals",
            "type": "t_mapping(t_address,t_bool)",
            "src": "../@rarible/tokens/contracts/erc-1155/ERC1155DefaultApproval.sol:8"
          },
          {
            "contract": "ERC1155DefaultApproval",
            "label": "__gap",
            "type": "t_array(t_uint256)50_storage",
            "src": "../@rarible/tokens/contracts/erc-1155/ERC1155DefaultApproval.sol:20"
          },
          {
            "contract": "ERC1155BurnableUpgradeable",
            "label": "__gap",
            "type": "t_array(t_uint256)50_storage",
            "src": "../@rarible/tokens/contracts/erc-1155/ERC1155BurnableUpgradeable.sol:40"
          },
          {
            "contract": "ERC1155BaseURI",
            "label": "_tokenURIs",
            "type": "t_mapping(t_uint256,t_string_storage)",
            "src": "../@rarible/tokens/contracts/erc-1155/ERC1155BaseURI.sol:12"
          },
          {
            "contract": "ERC1155BaseURI",
            "label": "_baseURI",
            "type": "t_string_storage",
            "src": "../@rarible/tokens/contracts/erc-1155/ERC1155BaseURI.sol:15"
          },
          {
            "contract": "ERC1155BaseURI",
            "label": "__gap",
            "type": "t_array(t_uint256)50_storage",
            "src": "../@rarible/tokens/contracts/erc-1155/ERC1155BaseURI.sol:67"
          },
          {
            "contract": "EIP712Upgradeable",
            "label": "_HASHED_NAME",
            "type": "t_bytes32",
            "src": "../@openzeppelin/contracts-upgradeable/drafts/EIP712Upgradeable.sol:27"
          },
          {
            "contract": "EIP712Upgradeable",
            "label": "_HASHED_VERSION",
            "type": "t_bytes32",
            "src": "../@openzeppelin/contracts-upgradeable/drafts/EIP712Upgradeable.sol:28"
          },
          {
            "contract": "EIP712Upgradeable",
            "label": "__gap",
            "type": "t_array(t_uint256)50_storage",
            "src": "../@openzeppelin/contracts-upgradeable/drafts/EIP712Upgradeable.sol:120"
          },
          {
            "contract": "ERC1271Validator",
            "label": "__gap",
            "type": "t_array(t_uint256)50_storage",
            "src": "../@rarible/tokens/contracts/erc-1271/ERC1271Validator.sol:30"
          },
          {
            "contract": "Mint1155Validator",
            "label": "__gap",
            "type": "t_array(t_uint256)50_storage",
            "src": "../@rarible/tokens/contracts/erc-1155/Mint1155Validator.sol:16"
          },
          {
            "contract": "AbstractRoyalties",
            "label": "royalties",
            "type": "t_mapping(t_uint256,t_array(t_struct(Part)9174_storage)dyn_storage)",
            "src": "../@rarible/royalties/contracts/impl/AbstractRoyalties.sol:8"
          },
          {
            "contract": "ERC1155Lazy",
            "label": "creators",
            "type": "t_mapping(t_uint256,t_array(t_struct(Part)9174_storage)dyn_storage)",
            "src": "../@rarible/tokens/contracts/erc-1155/ERC1155Lazy.sol:20"
          },
          {
            "contract": "ERC1155Lazy",
            "label": "supply",
            "type": "t_mapping(t_uint256,t_uint256)",
            "src": "../@rarible/tokens/contracts/erc-1155/ERC1155Lazy.sol:21"
          },
          {
            "contract": "ERC1155Lazy",
            "label": "minted",
            "type": "t_mapping(t_uint256,t_uint256)",
            "src": "../@rarible/tokens/contracts/erc-1155/ERC1155Lazy.sol:22"
          },
          {
            "contract": "ERC1155Lazy",
            "label": "__gap",
            "type": "t_array(t_uint256)50_storage",
            "src": "../@rarible/tokens/contracts/erc-1155/ERC1155Lazy.sol:136"
          },
          {
            "contract": "HasContractURI",
            "label": "contractURI",
            "type": "t_string_storage",
            "src": "../@rarible/tokens/contracts/HasContractURI.sol:9"
          },
          {
            "contract": "HasContractURI",
            "label": "__gap",
            "type": "t_array(t_uint256)49_storage",
            "src": "../@rarible/tokens/contracts/HasContractURI.sol:29"
          },
          {
            "contract": "ERC1155Base",
            "label": "name",
            "type": "t_string_storage",
            "src": "../@rarible/tokens/contracts/erc-1155/ERC1155Base.sol:14"
          },
          {
            "contract": "ERC1155Base",
            "label": "symbol",
            "type": "t_string_storage",
            "src": "../@rarible/tokens/contracts/erc-1155/ERC1155Base.sol:15"
          },
          {
            "contract": "ERC1155Base",
            "label": "__gap",
            "type": "t_array(t_uint256)50_storage",
            "src": "../@rarible/tokens/contracts/erc-1155/ERC1155Base.sol:42"
          },
          {
            "contract": "ERC1155Rarible",
            "label": "__gap",
            "type": "t_array(t_uint256)50_storage",
            "src": "../@rarible/tokens/contracts/erc-1155/ERC1155Rarible.sol:30"
          }
        ],
        "types": {
          "t_array(t_uint256)50_storage": {
            "label": "uint256[50]"
          },
          "t_uint256": {
            "label": "uint256"
          },
          "t_string_storage": {
            "label": "string"
          },
          "t_array(t_uint256)49_storage": {
            "label": "uint256[49]"
          },
          "t_mapping(t_uint256,t_array(t_struct(Part)9174_storage)dyn_storage)": {
            "label": "mapping(uint256 => struct LibPart.Part[])"
          },
          "t_array(t_struct(Part)9174_storage)dyn_storage": {
            "label": "struct LibPart.Part[]"
          },
          "t_struct(Part)9174_storage": {
            "label": "struct LibPart.Part",
            "members": [
              {
                "label": "account",
                "type": "t_address_payable"
              },
              {
                "label": "value",
                "type": "t_uint96"
              }
            ]
          },
          "t_address_payable": {
            "label": "address payable"
          },
          "t_uint96": {
            "label": "uint96"
          },
          "t_mapping(t_uint256,t_uint256)": {
            "label": "mapping(uint256 => uint256)"
          },
          "t_bytes32": {
            "label": "bytes32"
          },
          "t_mapping(t_uint256,t_string_storage)": {
            "label": "mapping(uint256 => string)"
          },
          "t_mapping(t_address,t_bool)": {
            "label": "mapping(address => bool)"
          },
          "t_address": {
            "label": "address"
          },
          "t_bool": {
            "label": "bool"
          },
          "t_mapping(t_uint256,t_mapping(t_address,t_uint256))": {
            "label": "mapping(uint256 => mapping(address => uint256))"
          },
          "t_mapping(t_address,t_uint256)": {
            "label": "mapping(address => uint256)"
          },
          "t_mapping(t_address,t_mapping(t_address,t_bool))": {
            "label": "mapping(address => mapping(address => bool))"
          },
          "t_array(t_uint256)47_storage": {
            "label": "uint256[47]"
          },
          "t_mapping(t_bytes4,t_bool)": {
            "label": "mapping(bytes4 => bool)"
          },
          "t_bytes4": {
            "label": "bytes4"
          }
        }
      }
    },
    "b3a80cccbdc8b3dc88413814a6a42833f4f598bd1d9b9deb1cfedfe0854d85d5": {
      "address": "0x64B70831292b7D1EBA4Bd1D73DbC94293843F04f",
      "txHash": "0x401fd9db4d5b017e9ab8002ba0b9c36b7d90aca7ba273fbf174e6f91d08598b4",
      "layout": {
        "storage": [
          {
            "contract": "Initializable",
            "label": "_initialized",
            "type": "t_bool",
            "src": "../@openzeppelin/contracts-upgradeable/proxy/Initializable.sol:25"
          },
          {
            "contract": "Initializable",
            "label": "_initializing",
            "type": "t_bool",
            "src": "../@openzeppelin/contracts-upgradeable/proxy/Initializable.sol:30"
          },
          {
            "contract": "ContextUpgradeable",
            "label": "__gap",
            "type": "t_array(t_uint256)50_storage",
            "src": "../@openzeppelin/contracts-upgradeable/utils/ContextUpgradeable.sol:31"
          },
          {
            "contract": "OwnableUpgradeable",
            "label": "_owner",
            "type": "t_address",
            "src": "../@openzeppelin/contracts-upgradeable/access/OwnableUpgradeable.sol:20"
          },
          {
            "contract": "OwnableUpgradeable",
            "label": "__gap",
            "type": "t_array(t_uint256)49_storage",
            "src": "../@openzeppelin/contracts-upgradeable/access/OwnableUpgradeable.sol:74"
          },
          {
            "contract": "ERC165Upgradeable",
            "label": "_supportedInterfaces",
            "type": "t_mapping(t_bytes4,t_bool)",
            "src": "../@openzeppelin/contracts-upgradeable/introspection/ERC165Upgradeable.sol:23"
          },
          {
            "contract": "ERC165Upgradeable",
            "label": "__gap",
            "type": "t_array(t_uint256)49_storage",
            "src": "../@openzeppelin/contracts-upgradeable/introspection/ERC165Upgradeable.sol:59"
          },
          {
            "contract": "EIP712Upgradeable",
            "label": "_HASHED_NAME",
            "type": "t_bytes32",
            "src": "../@openzeppelin/contracts-upgradeable/drafts/EIP712Upgradeable.sol:27"
          },
          {
            "contract": "EIP712Upgradeable",
            "label": "_HASHED_VERSION",
            "type": "t_bytes32",
            "src": "../@openzeppelin/contracts-upgradeable/drafts/EIP712Upgradeable.sol:28"
          },
          {
            "contract": "EIP712Upgradeable",
            "label": "__gap",
            "type": "t_array(t_uint256)50_storage",
            "src": "../@openzeppelin/contracts-upgradeable/drafts/EIP712Upgradeable.sol:120"
          },
          {
            "contract": "ERC1271Validator",
            "label": "__gap",
            "type": "t_array(t_uint256)50_storage",
            "src": "../@rarible/tokens/contracts/erc-1271/ERC1271Validator.sol:30"
          },
          {
            "contract": "ERC721UpgradeableMinimal",
            "label": "_name",
            "type": "t_string_storage",
            "src": "../@rarible/tokens-minimal/contracts/erc-721/ERC721UpgradeableMinimal.sol:23"
          },
          {
            "contract": "ERC721UpgradeableMinimal",
            "label": "_symbol",
            "type": "t_string_storage",
            "src": "../@rarible/tokens-minimal/contracts/erc-721/ERC721UpgradeableMinimal.sol:26"
          },
          {
            "contract": "ERC721UpgradeableMinimal",
            "label": "_owners",
            "type": "t_mapping(t_uint256,t_address)",
            "src": "../@rarible/tokens-minimal/contracts/erc-721/ERC721UpgradeableMinimal.sol:29"
          },
          {
            "contract": "ERC721UpgradeableMinimal",
            "label": "_balances",
            "type": "t_mapping(t_address,t_uint256)",
            "src": "../@rarible/tokens-minimal/contracts/erc-721/ERC721UpgradeableMinimal.sol:32"
          },
          {
            "contract": "ERC721UpgradeableMinimal",
            "label": "_tokenApprovals",
            "type": "t_mapping(t_uint256,t_address)",
            "src": "../@rarible/tokens-minimal/contracts/erc-721/ERC721UpgradeableMinimal.sol:35"
          },
          {
            "contract": "ERC721UpgradeableMinimal",
            "label": "_operatorApprovals",
            "type": "t_mapping(t_address,t_mapping(t_address,t_bool))",
            "src": "../@rarible/tokens-minimal/contracts/erc-721/ERC721UpgradeableMinimal.sol:38"
          },
          {
            "contract": "ERC721UpgradeableMinimal",
            "label": "__gap",
            "type": "t_array(t_uint256)44_storage",
            "src": "../@rarible/tokens-minimal/contracts/erc-721/ERC721UpgradeableMinimal.sol:432"
          },
          {
            "contract": "ERC721DefaultApprovalMinimal",
            "label": "defaultApprovals",
            "type": "t_mapping(t_address,t_bool)",
            "src": "../@rarible/tokens/contracts/erc-721-minimal/ERC721DefaultApprovalMinimal.sol:8"
          },
          {
            "contract": "ERC721DefaultApprovalMinimal",
            "label": "__gap",
            "type": "t_array(t_uint256)50_storage",
            "src": "../@rarible/tokens/contracts/erc-721-minimal/ERC721DefaultApprovalMinimal.sol:24"
          },
          {
            "contract": "ERC721BurnableUpgradeableMinimal",
            "label": "__gap",
            "type": "t_array(t_uint256)50_storage",
            "src": "../@rarible/tokens/contracts/erc-721-minimal/ERC721BurnableUpgradeableMinimal.sol:34"
          },
          {
            "contract": "Mint721Validator",
            "label": "__gap",
            "type": "t_array(t_uint256)50_storage",
            "src": "../@rarible/tokens/contracts/Mint721Validator.sol:16"
          },
          {
            "contract": "AbstractRoyalties",
            "label": "royalties",
            "type": "t_mapping(t_uint256,t_array(t_struct(Part)9174_storage)dyn_storage)",
            "src": "../@rarible/royalties/contracts/impl/AbstractRoyalties.sol:8"
          },
          {
            "contract": "ERC721URI",
            "label": "_tokenURIs",
            "type": "t_mapping(t_uint256,t_string_storage)",
            "src": "../@rarible/tokens/contracts/erc-721-minimal/ERC721URI.sol:18"
          },
          {
            "contract": "ERC721URI",
            "label": "_baseURI",
            "type": "t_string_storage",
            "src": "../@rarible/tokens/contracts/erc-721-minimal/ERC721URI.sol:21"
          },
          {
            "contract": "ERC721URI",
            "label": "__gap",
            "type": "t_array(t_uint256)50_storage",
            "src": "../@rarible/tokens/contracts/erc-721-minimal/ERC721URI.sol:93"
          },
          {
            "contract": "ERC721LazyMinimal",
            "label": "creators",
            "type": "t_mapping(t_uint256,t_array(t_struct(Part)9174_storage)dyn_storage)",
            "src": "../@rarible/tokens/contracts/erc-721-minimal/ERC721LazyMinimal.sol:23"
          },
          {
            "contract": "ERC721LazyMinimal",
            "label": "__gap",
            "type": "t_array(t_uint256)50_storage",
            "src": "../@rarible/tokens/contracts/erc-721-minimal/ERC721LazyMinimal.sol:112"
          },
          {
            "contract": "HasContractURI",
            "label": "contractURI",
            "type": "t_string_storage",
            "src": "../@rarible/tokens/contracts/HasContractURI.sol:9"
          },
          {
            "contract": "HasContractURI",
            "label": "__gap",
            "type": "t_array(t_uint256)49_storage",
            "src": "../@rarible/tokens/contracts/HasContractURI.sol:29"
          },
          {
            "contract": "ERC721BaseMinimal",
            "label": "__gap",
            "type": "t_array(t_uint256)50_storage",
            "src": "../@rarible/tokens/contracts/erc-721-minimal/ERC721BaseMinimal.sol:42"
          },
          {
            "contract": "ERC721RaribleMinimal",
            "label": "__gap",
            "type": "t_array(t_uint256)50_storage",
            "src": "../@rarible/tokens/contracts/erc-721-minimal/ERC721RaribleMinimal.sol:25"
          }
        ],
        "types": {
          "t_array(t_uint256)50_storage": {
            "label": "uint256[50]"
          },
          "t_uint256": {
            "label": "uint256"
          },
          "t_string_storage": {
            "label": "string"
          },
          "t_array(t_uint256)49_storage": {
            "label": "uint256[49]"
          },
          "t_mapping(t_uint256,t_array(t_struct(Part)9174_storage)dyn_storage)": {
            "label": "mapping(uint256 => struct LibPart.Part[])"
          },
          "t_array(t_struct(Part)9174_storage)dyn_storage": {
            "label": "struct LibPart.Part[]"
          },
          "t_struct(Part)9174_storage": {
            "label": "struct LibPart.Part",
            "members": [
              {
                "label": "account",
                "type": "t_address_payable"
              },
              {
                "label": "value",
                "type": "t_uint96"
              }
            ]
          },
          "t_address_payable": {
            "label": "address payable"
          },
          "t_uint96": {
            "label": "uint96"
          },
          "t_mapping(t_uint256,t_string_storage)": {
            "label": "mapping(uint256 => string)"
          },
          "t_mapping(t_address,t_bool)": {
            "label": "mapping(address => bool)"
          },
          "t_address": {
            "label": "address"
          },
          "t_bool": {
            "label": "bool"
          },
          "t_mapping(t_uint256,t_address)": {
            "label": "mapping(uint256 => address)"
          },
          "t_mapping(t_address,t_uint256)": {
            "label": "mapping(address => uint256)"
          },
          "t_mapping(t_address,t_mapping(t_address,t_bool))": {
            "label": "mapping(address => mapping(address => bool))"
          },
          "t_array(t_uint256)44_storage": {
            "label": "uint256[44]"
          },
          "t_bytes32": {
            "label": "bytes32"
          },
          "t_mapping(t_bytes4,t_bool)": {
            "label": "mapping(bytes4 => bool)"
          },
          "t_bytes4": {
            "label": "bytes4"
          }
        }
      }
    }
  }
}
